{"type":"Animation","props":{"y":0,"x":0,"source":"enemyThree.ani","width":83,"height":136,"pivotX":42,"name":"enemyThree","presetID":1,"isPresetRoot":true},"compId":178,"child":[{"type":"Label","props":{"text":"label","x":46,"y":-54,"width":116,"height":45,"pivotX":58,"pivotY":23,"color":"#ca0300","bold":true,"font":"Arial","fontSize":60,"visible":false,"presetID":2},"compId":179},{"type":"ProgressBar","props":{"skin":"comp/progress.png","width":120,"height":10,"x":42,"y":-17,"pivotX":60,"pivotY":5,"presetID":3},"compId":180},{"type":"Script","props":{"Modal":"@node:175","hero":"@node:110","hitLable":"@node:179","heroHitLable":"@node:146","enemyHPBar":"@node:180","enemyAttackDamage":10,"presetID":4,"runtime":"scripts/ememy/enemyThree.js"},"compId":181}],"loadList":["enemyThree.ani","comp/progress.png"],"loadList3D":[]}